torchevent/__init__.py
torchevent/artifacts.py
torchevent/layers.py
torchevent/loss.py
torchevent/metrics.py
torchevent/models.py
torchevent/profile.py
torchevent/transforms.py
torchevent/tsslbp.py
torchevent/utils.py
torchevent-0.0.3.dist-info/METADATA
torchevent-0.0.3.dist-info/WHEEL
torchevent-0.0.3.dist-info/entry_points.txt
torchevent-0.0.3.dist-info/top_level.txt
torchevent-0.0.3.dist-info/RECORD
