Metadata-Version: 2.1
Name: torchevent
Version: 0.0.3
Summary: A PyTorch library for event-based data processing
Home-page: https://github.com/devcow85/torchevent
Author: seokhun.jeon
Author-email: devcow85@gmail.com
Classifier: Development Status :: 4 - Beta
Classifier: Intended Audience :: Developers
Classifier: Programming Language :: Python :: 3
Classifier: Programming Language :: Python :: 3.10
Classifier: Programming Language :: Python :: 3.12
Classifier: Operating System :: OS Independent
Requires-Dist: torch
Requires-Dist: tonic
Requires-Dist: matplotlib
Requires-Dist: tqdm
Requires-Dist: pandas
Provides-Extra: dev
Requires-Dist: pytest; extra == "dev"
Requires-Dist: pytest-cov; extra == "dev"
